CHANGES.txt
LICENSE.txt
MANIFEST.in
README.txt
setup.py
js/__init__.py
js.html5boilerplate.egg-info/PKG-INFO
js.html5boilerplate.egg-info/SOURCES.txt
js.html5boilerplate.egg-info/dependency_links.txt
js.html5boilerplate.egg-info/entry_points.txt
js.html5boilerplate.egg-info/namespace_packages.txt
js.html5boilerplate.egg-info/not-zip-safe
js.html5boilerplate.egg-info/requires.txt
js.html5boilerplate.egg-info/top_level.txt
js/html5boilerplate/__init__.py
js/html5boilerplate/test_html5boilerplate.txt
js/html5boilerplate/resources/css/handheld-min.css
js/html5boilerplate/resources/css/handheld.css
js/html5boilerplate/resources/css/style-min.css
js/html5boilerplate/resources/css/style.css
js/html5boilerplate/resources/js/dd_belatedpng.js