Metadata-Version: 1.0
Name: js.html5boilerplate
Version: 1.0
Summary: Fanstatic packaging of html5boilerplate
Home-page: UNKNOWN
Author: Fanstatic Developers
Author-email: fanstatic@googlegroups.com
License: BSD
Platform: UNKNOWN
